README.md
license.txt
setup.py
test/test_tfidf_transformer.py
tfidf_transformation_brk/__init__.py
tfidf_transformation_brk/tfidf.py
tfidf_transformation_brk/tfidf_transformation_brk.py
tfidf_transformation_brk.egg-info/PKG-INFO
tfidf_transformation_brk.egg-info/SOURCES.txt
tfidf_transformation_brk.egg-info/dependency_links.txt
tfidf_transformation_brk.egg-info/top_level.txt